ats_utilities/__init__.py
ats_utilities/py.typed
ats_utilities/checker/__init__.py
ats_utilities/cli/__init__.py
ats_utilities/config_io/__init__.py
ats_utilities/config_io/file_check.py
ats_utilities/config_io/cfg/__init__.py
ats_utilities/config_io/cfg/cfg2object.py
ats_utilities/config_io/cfg/object2cfg.py
ats_utilities/config_io/ini/__init__.py
ats_utilities/config_io/ini/ini2object.py
ats_utilities/config_io/ini/object2ini.py
ats_utilities/config_io/json/__init__.py
ats_utilities/config_io/json/json2object.py
ats_utilities/config_io/json/object2json.py
ats_utilities/config_io/xml/__init__.py
ats_utilities/config_io/xml/object2xml.py
ats_utilities/config_io/xml/xml2object.py
ats_utilities/config_io/yaml/__init__.py
ats_utilities/config_io/yaml/object2yaml.py
ats_utilities/config_io/yaml/yaml2object.py
ats_utilities/console_io/__init__.py
ats_utilities/console_io/error.py
ats_utilities/console_io/success.py
ats_utilities/console_io/verbose.py
ats_utilities/console_io/warning.py
ats_utilities/exceptions/__init__.py
ats_utilities/exceptions/ats_attribute_error.py
ats_utilities/exceptions/ats_bad_call_error.py
ats_utilities/exceptions/ats_file_error.py
ats_utilities/exceptions/ats_key_error.py
ats_utilities/exceptions/ats_lookup_error.py
ats_utilities/exceptions/ats_parameter_error.py
ats_utilities/exceptions/ats_type_error.py
ats_utilities/exceptions/ats_value_error.py
ats_utilities/info/__init__.py
ats_utilities/info/ats_build_date.py
ats_utilities/info/ats_info_ok.py
ats_utilities/info/ats_licence.py
ats_utilities/info/ats_name.py
ats_utilities/info/ats_version.py
ats_utilities/logging/__init__.py
ats_utilities/option/__init__.py
ats_utilities/pro_config/__init__.py
ats_utilities/pro_config/pro_name.py
ats_utilities/pro_config/template_dir.py
ats_utilities/splash/__init__.py
ats_utilities/splash/ext_infrastructure.py
ats_utilities/splash/github_infrastructure.py
ats_utilities/splash/progress_bar.py
ats_utilities/splash/splash_property.py
ats_utilities-3.3.4.dist-info/licenses/LICENSE
ats_utilities-3.3.4.dist-info/METADATA
ats_utilities-3.3.4.dist-info/WHEEL
ats_utilities-3.3.4.dist-info/top_level.txt
ats_utilities-3.3.4.dist-info/RECORD
