Metadata-Version: 2.4
Name: ats_utilities
Version: 3.3.4
Summary: Python App/Tool/Script Utilities
Home-page: https://vroncevic.github.io/ats_utilities
Author: Vladimir Roncevic
Author-email: elektron.ronca@gmail.com
License: GPL-3.0-or-later
Keywords: util,config,log,option,xml,cfg,ini,json,yml,cli,meta
Platform: any
Classifier: Programming Language :: Python :: 3.10
Classifier: Programming Language :: Python :: 3.11
Classifier: Programming Language :: Python :: 3.12
License-File: LICENSE
Requires-Dist: colorama
Requires-Dist: bs4
Requires-Dist: lxml
Requires-Dist: PyYAML
Dynamic: author
Dynamic: author-email
Dynamic: classifier
Dynamic: description
Dynamic: description-content-type
Dynamic: home-page
Dynamic: keywords
Dynamic: license
Dynamic: license-file
Dynamic: platform
Dynamic: requires-dist
Dynamic: summary
